{"is_source_file": true, "format": "JavaScript (React component)", "description": "This file defines a React functional component named Header, which renders a header section with a title, a search input, and a 'New Note' button. It uses PropTypes for prop validation.", "external_files": ["prop-types"], "external_methods": [], "published": ["Header"], "classes": [], "methods": [{"name": "Header({ title, search, onSearchChange, onNewNote })", "description": "React functional component rendering header UI with title, search, and new note button.", "scope": "", "scopeKind": ""}], "calls": ["React", "PropTypes.string.isRequired", "PropTypes.func.isRequired", "onSearchChange(e.target.value)", "onNewNote()"], "search-terms": ["React functional component", "Header component", "prop-types validation", "search input", "new note button"], "state": 2, "file_id": 13, "knowledge_revision": 28, "git_revision": "", "ctags": [{"_type": "tag", "name": "Header", "path": "/home/kavia/workspace/code-generation/simple-notes-app-186420-186429/frontend_notes_app/src/components/Header.js", "pattern": "/^export default function Header({ title, search, onSearchChange, onNewNote }) {$/", "language": "JavaScript", "kind": "function", "signature": "({ title, search, onSearchChange, onNewNote })"}, {"_type": "tag", "name": "onNewNote", "path": "/home/kavia/workspace/code-generation/simple-notes-app-186420-186429/frontend_notes_app/src/components/Header.js", "pattern": "/^          onClick={onNewNote}$/", "language": "JavaScript", "kind": "field", "scope": "Header.onClick", "scopeKind": "class"}, {"_type": "tag", "name": "onNewNote", "path": "/home/kavia/workspace/code-generation/simple-notes-app-186420-186429/frontend_notes_app/src/components/Header.js", "pattern": "/^  onNewNote: PropTypes.func.isRequired,$/", "language": "JavaScript", "kind": "property", "scope": "Header.propTypes", "scopeKind": "class"}, {"_type": "tag", "name": "onSearchChange", "path": "/home/kavia/workspace/code-generation/simple-notes-app-186420-186429/frontend_notes_app/src/components/Header.js", "pattern": "/^  onSearchChange: PropTypes.func.isRequired,$/", "language": "JavaScript", "kind": "property", "scope": "Header.propTypes", "scopeKind": "class"}, {"_type": "tag", "name": "propTypes", "path": "/home/kavia/workspace/code-generation/simple-notes-app-186420-186429/frontend_notes_app/src/components/Header.js", "pattern": "/^Header.propTypes = {$/", "language": "JavaScript", "kind": "class", "scope": "Header", "scopeKind": "class"}, {"_type": "tag", "name": "search", "path": "/home/kavia/workspace/code-generation/simple-notes-app-186420-186429/frontend_notes_app/src/components/Header.js", "pattern": "/^          value={search}$/", "language": "JavaScript", "kind": "field", "scope": "Header.value", "scopeKind": "class"}, {"_type": "tag", "name": "search", "path": "/home/kavia/workspace/code-generation/simple-notes-app-186420-186429/frontend_notes_app/src/components/Header.js", "pattern": "/^  search: PropTypes.string.isRequired,$/", "language": "JavaScript", "kind": "property", "scope": "Header.propTypes", "scopeKind": "class"}, {"_type": "tag", "name": "title", "path": "/home/kavia/workspace/code-generation/simple-notes-app-186420-186429/frontend_notes_app/src/components/Header.js", "pattern": "/^  title: PropTypes.string.isRequired,$/", "language": "JavaScript", "kind": "property", "scope": "Header.propTypes", "scopeKind": "class"}], "hash": "cdf09c8a1a7eab061f666abf9a839caa", "format-version": 4, "code-base-name": "frontend_notes_app", "filename": "frontend_notes_app/src/components/Header.js", "fields": [{"name": "onClick={onNewNote}", "scope": "Header.onClick", "scopeKind": "class", "description": "unavailable"}, {"name": "onNewNote: PropTypes.func.isRequired,", "scope": "Header.propTypes", "scopeKind": "class", "description": "unavailable"}, {"name": "onSearchChange: PropTypes.func.isRequired,", "scope": "Header.propTypes", "scopeKind": "class", "description": "unavailable"}, {"name": "value={search}", "scope": "Header.value", "scopeKind": "class", "description": "unavailable"}, {"name": "search: PropTypes.string.isRequired,", "scope": "Header.propTypes", "scopeKind": "class", "description": "unavailable"}, {"name": "title: PropTypes.string.isRequired,", "scope": "Header.propTypes", "scopeKind": "class", "description": "unavailable"}], "revision_history": [{"28": ""}]}